mle/__init__.py
mle/features.py
mle/text.py
mle-0.0.3.dist-info/LICENSE
mle-0.0.3.dist-info/METADATA
mle-0.0.3.dist-info/WHEEL
mle-0.0.3.dist-info/top_level.txt
mle-0.0.3.dist-info/RECORD
