Metadata-Version: 2.1
Name: mle
Version: 0.0.3
Summary: Utilities for common DS/ML/AI tasks.
Home-page: https://github.com/dremok/mustard-light-emerald
Author: dremok
Author-email: max.y.leander@gmail.com
License: UNKNOWN
Platform: UNKNOWN
Classifier: Programming Language :: Python :: 3
Classifier: License :: OSI Approved :: MIT License
Classifier: Operating System :: OS Independent
Requires-Dist: pandas
Requires-Dist: scikit-learn
